libname/__init__.py
libname/hello.py
hellomk-0.0.1.dist-info/METADATA
hellomk-0.0.1.dist-info/WHEEL
hellomk-0.0.1.dist-info/top_level.txt
hellomk-0.0.1.dist-info/RECORD
