Metadata-Version: 2.1
Name: hellomk
Version: 0.0.1
Summary: this is a demo how how to create a pypi package
Home-page: https://github.com/MWFK/HelloWorldAPITest
Author: MXK
Author-email: themwfk@gmail.com
License: apache licence 2.0
Platform: UNKNOWN
